sudosearch/__init__.py
sudosearch/spacy_keywords.py
sudosearch-0.3.0.dist-info/WHEEL
sudosearch-0.3.0.dist-info/METADATA
sudosearch-0.3.0.dist-info/RECORD
